aite/__init__.py
aite/cli.py
aite-0.1.0.dist-info/METADATA
aite-0.1.0.dist-info/WHEEL
aite-0.1.0.dist-info/entry_points.txt
aite-0.1.0.dist-info/top_level.txt
aite-0.1.0.dist-info/RECORD
