Metadata-Version: 2.4
Name: aite
Version: 0.1.0
Summary: 人工智能测试与评估工具包
Author: xzhewei
Author-email: xzhewei@gmail.com
Classifier: Development Status :: 3 - Alpha
Classifier: Intended Audience :: Developers
Classifier: Topic :: Software Development :: Testing
Classifier: Programming Language :: Python :: 3
Classifier: Programming Language :: Python :: 3.7
Classifier: Programming Language :: Python :: 3.8
Classifier: Programming Language :: Python :: 3.9
Classifier: License :: OSI Approved :: MIT License
Classifier: Operating System :: OS Independent
Requires-Python: >=3.7
Requires-Dist: fastapi<0.69.0,>=0.68.0
Requires-Dist: pydantic<2.0.0,>=1.8.0
Requires-Dist: uvicorn<0.16.0,>=0.15.0
Dynamic: author
Dynamic: author-email
Dynamic: classifier
Dynamic: description
Dynamic: description-content-type
Dynamic: requires-dist
Dynamic: requires-python
Dynamic: summary
